qli/__init__.py
qli/qli_parser.py
qli/qli_svg.py
qli/qli_to_svg.py
qli/value_type.py
qli-0.1.3.dist-info/METADATA
qli-0.1.3.dist-info/WHEEL
qli-0.1.3.dist-info/licenses/LICENSE
qli-0.1.3.dist-info/RECORD
