Metadata-Version: 2.4
Name: qli
Version: 0.1.3
Summary: QLI File Parser and SVG Conversion Tool
Project-URL: Homepage, https://github.com/owebeeone/qli_to_svg
Project-URL: Bug Tracker, https://github.com/owebeeone/qli_to_svg/issues
Author-email: Gianni Mariani <gianni@mariani.ws>
License-File: LICENSE
Classifier: License :: OSI Approved :: GNU Lesser General Public License v2 or later (LGPLv2+)
Classifier: Operating System :: OS Independent
Classifier: Programming Language :: Python :: 3
Requires-Python: >=3.9
Requires-Dist: datatrees>=0.1.9
Requires-Dist: debugpy
Requires-Dist: frozendict
Requires-Dist: numpy
Requires-Dist: svg-path
